odoo8_addon_mgmtsystem_claim-8.0.1.1.0.99.dev14-py2.7-nspkg.pth
odoo8_addon_mgmtsystem_claim-8.0.1.1.0.99.dev14.dist-info/DESCRIPTION.rst
odoo8_addon_mgmtsystem_claim-8.0.1.1.0.99.dev14.dist-info/METADATA
odoo8_addon_mgmtsystem_claim-8.0.1.1.0.99.dev14.dist-info/RECORD
odoo8_addon_mgmtsystem_claim-8.0.1.1.0.99.dev14.dist-info/WHEEL
odoo8_addon_mgmtsystem_claim-8.0.1.1.0.99.dev14.dist-info/metadata.json
odoo8_addon_mgmtsystem_claim-8.0.1.1.0.99.dev14.dist-info/namespace_packages.txt
odoo8_addon_mgmtsystem_claim-8.0.1.1.0.99.dev14.dist-info/top_level.txt
odoo_addons/mgmtsystem_claim/__init__.py
odoo_addons/mgmtsystem_claim/__openerp__.py
odoo_addons/mgmtsystem_claim/workflow_mgmtsystem_claim.xml
odoo_addons/mgmtsystem_claim/data/claim_sequence.xml
odoo_addons/mgmtsystem_claim/data/mgmtsystem_claim_stage.xml
odoo_addons/mgmtsystem_claim/i18n/de.po
odoo_addons/mgmtsystem_claim/i18n/es.po
odoo_addons/mgmtsystem_claim/i18n/fr.po
odoo_addons/mgmtsystem_claim/i18n/hr.po
odoo_addons/mgmtsystem_claim/i18n/id.po
odoo_addons/mgmtsystem_claim/i18n/mgmtsystem_claim.pot
odoo_addons/mgmtsystem_claim/i18n/nb.po
odoo_addons/mgmtsystem_claim/i18n/pt_BR.po
odoo_addons/mgmtsystem_claim/i18n/sl.po
odoo_addons/mgmtsystem_claim/i18n/sv.po
odoo_addons/mgmtsystem_claim/i18n/vi.po
odoo_addons/mgmtsystem_claim/models/__init__.py
odoo_addons/mgmtsystem_claim/models/mgmtsystem_claim.py
odoo_addons/mgmtsystem_claim/models/mgmtsystem_claim_stage.py
odoo_addons/mgmtsystem_claim/security/ir.model.access.csv
odoo_addons/mgmtsystem_claim/security/mgmtsystem_claim_security.xml
odoo_addons/mgmtsystem_claim/static/description/icon.png
odoo_addons/mgmtsystem_claim/tests/__init__.py
odoo_addons/mgmtsystem_claim/tests/test_create_claim.py
odoo_addons/mgmtsystem_claim/views/board_mgmtsystem_claim.xml
odoo_addons/mgmtsystem_claim/views/menus.xml
odoo_addons/mgmtsystem_claim/views/mgmtsystem_claim.xml
odoo_addons/mgmtsystem_claim/views/mgmtsystem_claim_stage.xml
